cuddly_octo_funicular/__init__.py
cuddly_octo_funicular/__main__.py
cuddly_octo_funicular/logging/__init__.py
cuddly_octo_funicular/logging/_logging.py
cuddly_octo_funicular/utils/__init__.py
cuddly_octo_funicular/utils/_utils.py
cuddly_octo_funicular-0.0.8.dist-info/LICENSE
cuddly_octo_funicular-0.0.8.dist-info/METADATA
cuddly_octo_funicular-0.0.8.dist-info/WHEEL
cuddly_octo_funicular-0.0.8.dist-info/entry_points.txt
cuddly_octo_funicular-0.0.8.dist-info/top_level.txt
cuddly_octo_funicular-0.0.8.dist-info/RECORD
