Metadata-Version: 2.1
Name: cuddly-octo-funicular
Version: 0.0.8
Home-page: https://github.com/yu9824/cuddly-octo-funicular
Author: yu9824
Maintainer: yu9824
License: MIT License
Project-URL: Homepage, https://github.com/yu9824/cuddly-octo-funicular
Project-URL: PyPI, https://pypi.org/project/cuddly-octo-funicular/
Project-URL: Source, https://github.com/yu9824/cuddly-octo-funicular
Project-URL: Tracker, https://github.com/yu9824/cuddly-octo-funicular/issues
Project-URL: Changelog, https://github.com/yu9824/cuddly-octo-funicular/blob/main/CHANGELOG.md
Classifier: Programming Language :: Python :: 3
Classifier: Programming Language :: Python :: 3.8
Classifier: Programming Language :: Python :: 3.9
Classifier: Programming Language :: Python :: 3.10
Classifier: Programming Language :: Python :: 3.11
Classifier: Programming Language :: Python :: 3.12
Classifier: Programming Language :: Python :: 3.13
Classifier: License :: OSI Approved :: MIT License
Requires-Python: >=3.7
License-File: LICENSE
Provides-Extra: dev
Requires-Dist: build ; extra == 'dev'
Provides-Extra: docs
Requires-Dist: sphinx ; extra == 'docs'
Requires-Dist: sphinx-rtd-theme ; extra == 'docs'
Requires-Dist: sphinx-markdown-tables ; extra == 'docs'
Requires-Dist: recommonmark ; extra == 'docs'
Provides-Extra: gui
Requires-Dist: TkEasyGUI ; extra == 'gui'
Provides-Extra: optional
Requires-Dist: colorlog ; extra == 'optional'
Requires-Dist: tqdm ; extra == 'optional'
Provides-Extra: test
Requires-Dist: pytest ; extra == 'test'
